{
    "nav_home":"Home",
    "nav_shop":"Explore",
    "nav_create":"Create course",
    "nav_myCourses":"My Courses",
    "nav_account":"Account",
    "nav_reedem":"Reedem course",
    "nav_settings":"Settings",
    "nav_logout":"Logout",
    "nav_welcome_msg":"Hello",
    "addCourse_title":"Let's create something interesting!",
    "addCourse_cName":"Course name",
    "addCourse_description":"Course description",
    "addCourse_requirements":"Course requirements",
    "addCourse_thumbnail":"Add a thumbnail to course",
    "btn_create":"Create!",
    "course_domain_placeholder":"Your course is about",
    "course_domain_ALL":"ALL",
    "course_domain_IT":"IT",
    "course_domain_Design":"Design",
    "course_domain_3D":"3D Graphics",
    "index_sugestions":"You may me be interested:",
    "shop_description":"Description",
    "shop_requirements":"Requirements",
    "getCourse":"Get Course!",
    "user_creations":"My creations",
    "user_courses":"My learning",
    "user_courses_create_inv":"Create invite code",
    "course_page_addBtn":"Add new item",
    "course_page_theory":"THEORY",
    "course_page_videos":"VIDEOS",
    "btn_close":"CLOSE",
    "course_page_tasks":"TASKS",
    "course_page_show_submits":"Show all test submits",
    "course_page_home":"Back",
    "add_content_topic":"Course topic",
    "add_content_video":"Video topic",
    "add_content_task":"Task",
    "add_content_title":"How this topic will be named?",
    "subtopic_title":"Subtopic title",
    "subtopic_content":"Subtopic content",
    "upload_image":"Add an image to this topic",
    "subtopic_add_more":"Add subtopic",
    "subtopic_video_description":"Enter description for this video!",
    "add_video":"Click here to upload video!",
    "add_multichoice":"Multichoice question",
    "add_question":"Question with answer field",
    "add_task":"Question with upload field",
    "subtopic_question":"Enter the question",
    "suptopic_multichoice_answer":"Enter the answer variant. Check if it's the right one! ->",
    "subtopic_multichoice_option":"Add option",
    "subtopic_answer":"Place the right answer here or just leave it plain",
    "subtopic_task":"Enter the question for the task",
    "var_nums_limit":"Variants are limited!",
    "landing_welcome":"WELCOME!",
    "landing_first_msg":"Please SIGN IN!",
    "landing_uname":"Username",
    "landing_password":"Password",
    "landing_second_msg":"Forgot password?",
    "landing_login":"SIGN IN",
    "landing_third_msg":"Not a member? Please ",
    "action_register":"Sign Up",
    "landing_welcome2":"Hi!",
    "landing_fifth_msg":"Please SIGN UP!",
    "landing_name":"Your real name",
    "landing_mail":"E-mail",
    "landing_repassword":"Re-enter password",
    "landing_who":"You are",
    "landing_teacher":"Teacher",
    "landing_student":"Student",
    "landing_interest":"You're interested in",
    "landing_interest_other":"Other",
    "landing_register":"Register",
    "landing_fourth_msg":"Alredy a member? You may ",
    "action_login":"Sign In",
    "reg_wrong_password":"Passwords doesn't match!",
    "settings_lang":"Set language",
    "reedem_exp":"Time to expire",
    "password_length_alert":"Password should be at least 8 characters long!"
}